resource_availability_monitoring/__init__.py
resource_availability_monitoring/__main__.py
resource_availability_monitoring/condor_job.py
resource_availability_monitoring/default_configuration/config.yml
resource_availability_monitoring/default_configuration/default/default.sh
resource_availability_monitoring/default_configuration/influx_parameters.yml
resource_availability_monitoring/influx_db_writer.py
resource_availability_monitoring/job_database.py
resource_availability_monitoring/job_factory.py
resource_availability_monitoring/job_scheduler.py
resource_availability_monitoring-0.2.8.dist-info/LICENSE
resource_availability_monitoring-0.2.8.dist-info/METADATA
resource_availability_monitoring-0.2.8.dist-info/WHEEL
resource_availability_monitoring-0.2.8.dist-info/entry_points.txt
resource_availability_monitoring-0.2.8.dist-info/RECORD
