Metadata-Version: 2.1
Name: resource-availability-monitoring
Version: 0.2.8
Summary: A simple resource monitoring tool, that can be used to test availability of HTCondor resources.
License: {file = "LICENSE"}
Author: Sebastian Brommer
Author-email: brommer.sebastian@gmail.com
Requires-Python: >=3.8,<4.0
Classifier: Development Status :: 3 - Alpha
Classifier: Intended Audience :: Developers
Classifier: Intended Audience :: Science/Research
Classifier: License :: OSI Approved :: GNU General Public License v3 (GPLv3)
Classifier: License :: Other/Proprietary License
Classifier: Operating System :: OS Independent
Classifier: Programming Language :: Python :: 3
Classifier: Programming Language :: Python :: 3.8
Classifier: Programming Language :: Python :: 3.9
Classifier: Programming Language :: Python :: 3.10
Classifier: Programming Language :: Python :: 3.11
Classifier: Programming Language :: Python :: 3.12
Classifier: Topic :: Scientific/Engineering
Classifier: Topic :: System :: Clustering
Classifier: Topic :: System :: Distributed Computing
Classifier: Topic :: System :: Monitoring
Classifier: Topic :: System :: Systems Administration
Classifier: Topic :: Utilities
Requires-Dist: PyYAML (>=6.0.1,<7.0.0)
Requires-Dist: htcondor (>=23.4.0,<24.0.0)
Requires-Dist: influxdb-client (>=1.40.0,<2.0.0)
Requires-Dist: schedule (>=1.2.1,<2.0.0)
